MuEnvironment/CommonBuildEntry.py
MuEnvironment/ConfMgmt.py
MuEnvironment/EnvironmentDescriptorFiles.py
MuEnvironment/ExternalDependency.py
MuEnvironment/GitDependency.py
MuEnvironment/MuGit.py
MuEnvironment/MuLogging.py
MuEnvironment/MultipleWorkspace.py
MuEnvironment/NugetDependency.py
MuEnvironment/NugetPublishing.py
MuEnvironment/Omnicache.py
MuEnvironment/PluginManager.py
MuEnvironment/RepoResolver.py
MuEnvironment/SelfDescribingEnvironment.py
MuEnvironment/ShellEnvironment.py
MuEnvironment/UefiBuild.py
MuEnvironment/VarDict.py
MuEnvironment/VersionAggregator.py
MuEnvironment/WebDependency.py
MuEnvironment/__init__.py
MuEnvironment/bin/NuGet.exe
MuEnvironment/bin/NuGet.py
MuEnvironment/bin/__init__.py
MuEnvironment/bin/readme.md
MuEnvironment/docs/feature_MuLogging.md
MuEnvironment/docs/feature_extdep.md
MuEnvironment/docs/feature_nugetpublishing.md
MuEnvironment/docs/feature_omnicache.md
MuEnvironment/docs/feature_pluginmanager.md
MuEnvironment/docs/feature_sde.md
MuEnvironment/tests/test_GitDependency.py
MuEnvironment/tests/test_MuLogging.py
MuEnvironment/tests/test_RepoResolver.py
MuEnvironment/tests/test_ShellEnvironment.py
MuEnvironment/tests/test_WebDependency.py
MuEnvironment/tests/test_omnicache.py
mu_environment-0.3.15.dist-info/LICENSE
mu_environment-0.3.15.dist-info/METADATA
mu_environment-0.3.15.dist-info/WHEEL
mu_environment-0.3.15.dist-info/entry_points.txt
mu_environment-0.3.15.dist-info/top_level.txt
mu_environment-0.3.15.dist-info/RECORD
