Metadata-Version: 2.1
Name: mu-environment
Version: 0.3.15
Summary: Project Mu distributed dependency management, build, test, and tool environments.
Home-page: https://github.com/microsoft/mu_pip_environment
Author: Project Mu Team
Author-email: maknutse@microsoft.com
License: BSD2
Platform: UNKNOWN
Classifier: Programming Language :: Python :: 3
Classifier: License :: OSI Approved :: BSD License
Classifier: Operating System :: OS Independent
Classifier: Development Status :: 4 - Beta
Requires-Dist: pyyaml
Requires-Dist: mu-python-library (>=0.4.6)
